py.py
_pytest/__init__.py
_pytest/_argcomplete.py
_pytest/_version.py
_pytest/cacheprovider.py
_pytest/capture.py
_pytest/compat.py
_pytest/deprecated.py
_pytest/faulthandler.py
_pytest/fixtures.py
_pytest/freeze_support.py
_pytest/helpconfig.py
_pytest/hookspec.py
_pytest/junitxml.py
_pytest/legacypath.py
_pytest/logging.py
_pytest/main.py
_pytest/monkeypatch.py
_pytest/nodes.py
_pytest/outcomes.py
_pytest/pathlib.py
_pytest/py.typed
_pytest/pytester.py
_pytest/pytester_assertions.py
_pytest/python.py
_pytest/python_api.py
_pytest/recwarn.py
_pytest/reports.py
_pytest/runner.py
_pytest/scope.py
_pytest/setuponly.py
_pytest/setupplan.py
_pytest/skipping.py
_pytest/stash.py
_pytest/stepwise.py
_pytest/terminal.py
_pytest/threadexception.py
_pytest/timing.py
_pytest/tmpdir.py
_pytest/unraisableexception.py
_pytest/warning_types.py
_pytest/warnings.py
_pytest/_code/__init__.py
_pytest/_code/code.py
_pytest/_code/source.py
_pytest/_io/__init__.py
_pytest/_io/pprint.py
_pytest/_io/saferepr.py
_pytest/_io/terminalwriter.py
_pytest/_io/wcwidth.py
_pytest/_py/__init__.py
_pytest/_py/error.py
_pytest/_py/path.py
_pytest/assertion/__init__.py
_pytest/assertion/rewrite.py
_pytest/assertion/truncate.py
_pytest/assertion/util.py
_pytest/config/__init__.py
_pytest/config/argparsing.py
_pytest/config/compat.py
_pytest/config/exceptions.py
_pytest/config/findpaths.py
_pytest/mark/__init__.py
_pytest/mark/expression.py
_pytest/mark/structures.py
pytest/__init__.py
pytest/__main__.py
pytest/py.typed
ok-0.832.4.dist-info/AUTHORS
ok-0.832.4.dist-info/LICENSE
ok-0.832.4.dist-info/METADATA
ok-0.832.4.dist-info/WHEEL
ok-0.832.4.dist-info/entry_points.txt
ok-0.832.4.dist-info/top_level.txt
ok-0.832.4.dist-info/RECORD
